{
    "$schema": "https://schema.management.azure.com/schemas/2019-04-01/deploymentTemplate.json#",
    "contentVersion": "1.0.0.0",
    "parameters": {
        "storage_account_name": {
            "type": "String"
        },
        "location": {
            "type": "String"
        }
    },
    "variables": {},
    "resources": [
        {
            "type": "Microsoft.Storage/storageAccounts",
            "apiVersion": "2021-09-01",
            "name": "[parameters('storage_account_name')]",
            "location": "[parameters('location')]",
            "sku": {
                "name": "Standard_LRS",
                "tier": "Standard"
            },
            "kind": "StorageV2",
            "properties": {
                "minimumTlsVersion": "TLS1_0",
                "allowBlobPublicAccess": true,
                "networkAcls": {
                    "bypass": "AzureServices",
                    "virtualNetworkRules": [],
                    "ipRules": [],
                    "defaultAction": "Allow"
                },
                "supportsHttpsTrafficOnly": true,
                "encryption": {
                    "services": {
                        "file": {
                            "keyType": "Account",
                            "enabled": true
                        },
                        "blob": {
                            "keyType": "Account",
                            "enabled": true
                        }
                    },
                    "keySource": "Microsoft.Storage"
                },
                "accessTier": "Hot"
            }
        },
        {
            "type": "Microsoft.Storage/storageAccounts/blobServices",
            "apiVersion": "2021-09-01",
            "name": "[concat(parameters('storage_account_name'), '/default')]",
            "dependsOn": [
                "[resourceId('Microsoft.Storage/storageAccounts', parameters('storage_account_name'))]"
            ],
            "sku": {
                "name": "Standard_LRS",
                "tier": "Standard"
            },
            "properties": {
                "cors": {
                    "corsRules": []
                },
                "deleteRetentionPolicy": {
                    "allowPermanentDelete": false,
                    "enabled": false
                }
            }
        },
        {
            "type": "Microsoft.Storage/storageAccounts/blobServices/containers",
            "apiVersion": "2021-09-01",
            "name": "[concat(parameters('storage_account_name'), '/default/bacpacs')]",
            "dependsOn": [
                "[resourceId('Microsoft.Storage/storageAccounts/blobServices', parameters('storage_account_name'), 'default')]",
                "[resourceId('Microsoft.Storage/storageAccounts', parameters('storage_account_name'))]"
            ],
            "properties": {
                "immutableStorageWithVersioning": {
                    "enabled": false
                },
                "defaultEncryptionScope": "$account-encryption-key",
                "denyEncryptionScopeOverride": false,
                "publicAccess": "None"
            }
        }
    ]
}
